LICENSE
README.md
setup.py
src/pyfeats/__init__.py
src/pyfeats/utilities.py
src/pyfeats.egg-info/PKG-INFO
src/pyfeats.egg-info/SOURCES.txt
src/pyfeats.egg-info/dependency_links.txt
src/pyfeats.egg-info/requires.txt
src/pyfeats.egg-info/top_level.txt
src/pyfeats/histogram/__init__.py
src/pyfeats/histogram/correlogram.py
src/pyfeats/histogram/histogram.py
src/pyfeats/histogram/multiregion_histogram.py
src/pyfeats/morphological/__init__.py
src/pyfeats/morphological/grayscale_morphological_analysis.py
src/pyfeats/morphological/multilevel_binary_morphological_analysis.py
src/pyfeats/multiscale/__init__.py
src/pyfeats/multiscale/amfm.py
src/pyfeats/multiscale/dwt.py
src/pyfeats/multiscale/fdta.py
src/pyfeats/multiscale/gt.py
src/pyfeats/multiscale/swt.py
src/pyfeats/multiscale/wp.py
src/pyfeats/other/__init__.py
src/pyfeats/other/hog.py
src/pyfeats/other/hu.py
src/pyfeats/other/tas.py
src/pyfeats/other/zernikes.py
src/pyfeats/textural/__init__.py
src/pyfeats/textural/bispectrum.py
src/pyfeats/textural/fdta.py
src/pyfeats/textural/fos.py
src/pyfeats/textural/fps.py
src/pyfeats/textural/glcm.py
src/pyfeats/textural/glds.py
src/pyfeats/textural/glrlm.py
src/pyfeats/textural/glszm.py
src/pyfeats/textural/hos.py
src/pyfeats/textural/hos_v2.py
src/pyfeats/textural/lbp.py
src/pyfeats/textural/lte.py
src/pyfeats/textural/ngtdm.py
src/pyfeats/textural/sfm.py
src/pyfeats/textural/shape_parameters.py