Metadata-Version: 2.1
Name: pyfeats
Version: 1.0.1
Summary: Open-source software for image feature extraction
Home-page: https://github.com/giakou4/pyfeats
Author: Nikolaos G. Giakoumoglou
Author-email: <nikolaos.giakoumoglou@gmail.com>
License: MIT
Keywords: python,image,region-of-interest,mask,features,polygon
Platform: Any
Classifier: Development Status :: 5 - Production/Stable
Classifier: Intended Audience :: Developers
Classifier: Intended Audience :: Science/Research
Classifier: Topic :: Scientific/Engineering :: Image Recognition
Classifier: Topic :: Software Development :: Libraries
Classifier: Programming Language :: Python :: 3
Classifier: License :: OSI Approved :: MIT License
Classifier: Operating System :: Unix
Classifier: Operating System :: MacOS :: MacOS X
Classifier: Operating System :: Microsoft :: Windows
License-File: LICENSE
